finance_simulate/__init__.py
finance_simulate-1.0.0.dev1.dist-info/METADATA
finance_simulate-1.0.0.dev1.dist-info/WHEEL
finance_simulate-1.0.0.dev1.dist-info/top_level.txt
finance_simulate-1.0.0.dev1.dist-info/RECORD
